{ "nodes": [
{"id": "quick-cscope-emacs-hack", "label": "quick-cscope-emacs-hack"},
{"id": "emacs_on_android", "label": "emacs_on_android"},
{"id": "termux-setup", "label": "termux-setup"},
{"id": "yaava-mohana", "label": "yaava-mohana"},
{"id": "literate_programming", "label": "literate_programming"},
{"id": "luck_and_risk", "label": "luck_and_risk"},
{"id": "configuration", "label": "configuration"},
{"id": "tmux-config", "label": "tmux-config"},
{"id": "rehna-tu", "label": "rehna-tu"},
{"id": "org_mode", "label": "org_mode"},
{"id": "music", "label": "music"},
{"id": "org_roam", "label": "org_roam"},
{"id": "writing-music-chords", "label": "writing-music-chords"},
{"id": "emacs", "label": "emacs"},
{"id": "dil-mein-jagi", "label": "dil-mein-jagi"},
], 
 "edges": [
{"from": "literate_programming", "to": "termux-setup"},
{"from": "org_roam", "to": "emacs_on_android"},
{"from": "literate_programming", "to": "tmux-config"},
{"from": "configuration", "to": "org_mode"},
{"from": "emacs_on_android", "to": "termux-setup"},
{"from": "org_mode", "to": "literate_programming"},
{"from": "org_mode", "to": "emacs_on_android"},
{"from": "music", "to": "rehna-tu"},
{"from": "literate_programming", "to": "configuration"},
{"from": "org_mode", "to": "configuration"},
{"from": "emacs", "to": "termux-setup"},
{"from": "termux-setup", "to": "emacs_on_android"},
{"from": "emacs", "to": "configuration"},
{"from": "music", "to": "writing-music-chords"},
{"from": "music", "to": "dil-mein-jagi"},
]}
